whitenoise/__init__.py
whitenoise/tests.py
whitenoise/fixtures.py
whitenoise/random/__init__.py
whitenoise/random/random_string.py
whitenoise/random/tests/__init__.py
whitenoise/random/tests/test_random.py
whitenoise/generators/__init__.py
whitenoise/generators/sqlalchemy.py
whitenoise/generators/simple.py
White_Noise-0.1.0.dist-info/DESCRIPTION.rst
White_Noise-0.1.0.dist-info/METADATA
White_Noise-0.1.0.dist-info/RECORD
White_Noise-0.1.0.dist-info/metadata.json
White_Noise-0.1.0.dist-info/top_level.txt
White_Noise-0.1.0.dist-info/WHEEL
