Metadata-Version: 1.1
Name: White-Noise
Version: 0.1.0
Summary: An SQLAlchemy test data (fixture) generator
Home-page: https://github.com/James1345/white-noise
Author: James McMahon
Author-email: james1345@googlemail.com
License: MIT
Keywords: fixture SQLAlchemy ORM generator
Platform: UNKNOWN
Classifier: Development Status :: 3 - Alpha
Classifier: Intended Audience :: Developers
Classifier: Topic :: Database
Classifier: License :: OSI Approved :: MIT License
Classifier: Programming Language :: Python :: 3
Classifier: Programming Language :: Python :: 3.4
